{
    "Frequencies": [
        4,
        4,
        4,
        4,
        8
    ],
    "MADOutliers": [
        4,
        4,
        4,
        4,
        8
    ],
    "MADTimestamps": [
        "2023-11-29T16:26:00-05:00",
        "2023-11-29T16:27:00-05:00",
        "2023-11-29T16:28:00-05:00",
        "2023-11-29T16:24:00-05:00",
        "2023-11-29T16:25:00-05:00"
    ],
    "ShakeAlertOutliers": [
        4,
        4,
        4,
        4,
        8
    ],
    "ShakeAlertTimestamps": []
}